lunar_birthday_ical/__init__.py
lunar_birthday_ical/calendar.py
lunar_birthday_ical/config.py
lunar_birthday_ical/holidays.py
lunar_birthday_ical/main.py
lunar_birthday_ical/uploader.py
lunar_birthday_ical/utils.py
lunar_birthday_ical-0.6.0.dist-info/METADATA
lunar_birthday_ical-0.6.0.dist-info/WHEEL
lunar_birthday_ical-0.6.0.dist-info/entry_points.txt
lunar_birthday_ical-0.6.0.dist-info/licenses/LICENSE
lunar_birthday_ical-0.6.0.dist-info/RECORD
