Metadata-Version: 2.4
Name: lunar-birthday-ical
Version: 0.6.0
Summary: A command line tool written in Python 3 for creating lunar birthday events
Project-URL: Homepage, https://github.com/ak1ra-lab/lunar-birthday-ical
Project-URL: Changelog, https://github.com/ak1ra-lab/lunar-birthday-ical/blob/master/CHANGELOG.md
Author-email: ak1ra <git@ak1ra.xyz>
License-Expression: MIT
License-File: LICENSE
Keywords: birthday,icalendar,lunar
Classifier: Development Status :: 4 - Beta
Classifier: Operating System :: OS Independent
Classifier: Programming Language :: Python :: 3
Classifier: Programming Language :: Python :: 3 :: Only
Classifier: Programming Language :: Python :: 3.11
Classifier: Programming Language :: Python :: 3.12
Classifier: Programming Language :: Python :: 3.13
Requires-Python: >=3.11
Requires-Dist: argcomplete>=3.5.3
Requires-Dist: chaos-utils>=0.1.2
Requires-Dist: httpx>=0.28.1
Requires-Dist: icalendar>=6.1.1
Requires-Dist: lunar-python>=1.3.12
Requires-Dist: pyyaml>=6.0.2
